MANIFEST.in
README.md
setup.cfg
setup.py
versioneer.py
pyqttoolkit/__init__.py
pyqttoolkit/_version.py
pyqttoolkit.egg-info/PKG-INFO
pyqttoolkit.egg-info/SOURCES.txt
pyqttoolkit.egg-info/dependency_links.txt
pyqttoolkit.egg-info/requires.txt
pyqttoolkit.egg-info/top_level.txt
pyqttoolkit/application/__init__.py
pyqttoolkit/application/application.py
pyqttoolkit/application/garbage_collector.py
pyqttoolkit/colors/__init__.py
pyqttoolkit/config/__init__.py
pyqttoolkit/config/base.py
pyqttoolkit/config/composite.py
pyqttoolkit/config/default.py
pyqttoolkit/config/environment.py
pyqttoolkit/config/multi_json_file.py
pyqttoolkit/config/with_signal.py
pyqttoolkit/config/with_value_changed.py
pyqttoolkit/data/__init__.py
pyqttoolkit/data/bits.py
pyqttoolkit/data/cache.py
pyqttoolkit/data/interval.py
pyqttoolkit/data/message.py
pyqttoolkit/data/names.py
pyqttoolkit/datetime/__init__.py
pyqttoolkit/datetime/datetime.py
pyqttoolkit/datetime/qdatetime.py
pyqttoolkit/dependencies/__init__.py
pyqttoolkit/errors/__init__.py
pyqttoolkit/exceptions/__init__.py
pyqttoolkit/filesystem/__init__.py
pyqttoolkit/logs/__init__.py
pyqttoolkit/metadata/__init__.py
pyqttoolkit/metadata/dataframe_metadata_manager.py
pyqttoolkit/metadata/dict_metadata_manager.py
pyqttoolkit/metadata/id_generator.py
pyqttoolkit/metadata/metadata_manager_base.py
pyqttoolkit/models/__init__.py
pyqttoolkit/models/code_text.py
pyqttoolkit/models/dataframetable.py
pyqttoolkit/models/dictpropertytree.py
pyqttoolkit/models/dicttable.py
pyqttoolkit/models/json_text.py
pyqttoolkit/models/list_model.py
pyqttoolkit/models/module.py
pyqttoolkit/models/roles.py
pyqttoolkit/models/series_data.py
pyqttoolkit/models/span.py
pyqttoolkit/models/validation.py
pyqttoolkit/modules/__init__.py
pyqttoolkit/modules/launcher_config.py
pyqttoolkit/modules/module.py
pyqttoolkit/modules/events/__init__.py
pyqttoolkit/modules/events/add_signal.py
pyqttoolkit/modules/events/module_opening.py
pyqttoolkit/modules/events/rejectable.py
pyqttoolkit/properties/__init__.py
pyqttoolkit/properties/auto.py
pyqttoolkit/properties/throttled.py
pyqttoolkit/scripting/__init__.py
pyqttoolkit/scripting/script_context.py
