Metadata-Version: 2.1
Name: pyqttoolkit
Version: 0.8.2
Summary: A toolkit for PyQt 5
Home-page: https://github.com/BitBloomTech/pyqttoolkit
Author: Bitbloom Ltd
Author-email: info@bitbloom.tech
License: GPLv3
Platform: any
Requires-Python: >=3.6
Provides-Extra: test
Provides-Extra: ui
Provides-Extra: publish
